<?xml version="1.0"?>
<opencv_storage>
<stage0>
  <maxWeakCount>5</maxWeakCount>
  <stageThreshold>-0.68982493877410889</stageThreshold>
  <weakClassifiers>
    <_>
      <internalNodes>
        0 -1 247429 -69469185 -707530095 -1056747107 -571010685
        -1177945153 -20741493 697027839 1005534187</internalNodes>
      <leafValues>
        -0.93324607610702515 0.095588237047195435</leafValues></_>
    <_>
      <internalNodes>
        0 -1 312374 -572525572 -169885537 1627512577 -540385 -775759686
        -877690740 -887366662 1068177839</internalNodes>
      <leafValues>
        -0.89056241512298584 0.38924157619476318</leafValues></_>
    <_>
      <internalNodes>
        0 -1 418837 -2033976833 -1575860141 302008671 -335527760
        -2145288031 -1929280511 -947789657 -323964464</internalNodes>
      <leafValues>
        -0.89203840494155884 0.46393877267837524</leafValues></_>
    <_>
      <internalNodes>
        0 -1 494046 -1783391393 -1388019583 -2146893819 -262537193
        1091076819 -900595561 -502592081 -1548471804</internalNodes>
      <leafValues>
        -0.78562253713607788 0.50667804479598999</leafValues></_>
    <_>
      <internalNodes>
        0 -1 522249 1802496262 333382031 1107398875 -1478535537
        -1601646084 1781045635 134996927 737147727</internalNodes>
      <leafValues>
        -0.78929442167282104 0.54426378011703491</leafValues></_></weakClassifiers></stage0>
</opencv_storage>
